fruity_menu/__init__.py
fruity_menu/abstract.py
fruity_menu/adjust.py
fruity_menu/menu.py
fruity_menu/options.py
fruity_display_menu-1.2.0.dist-info/LICENSE.md
fruity_display_menu-1.2.0.dist-info/METADATA
fruity_display_menu-1.2.0.dist-info/WHEEL
fruity_display_menu-1.2.0.dist-info/top_level.txt
fruity_display_menu-1.2.0.dist-info/RECORD
