Metadata-Version: 2.1
Name: fruity_display_menu
Version: 1.2.0
Summary: Simple menu library for CircuitPython devices, designed for Adafruit RP2040 macropad.
Home-page: https://git.therode.net/jrode/fruity_menu
Author: Jay Rode
Author-email: jay@rode.dev
License: Mozilla Public License 2.0
Classifier: Programming Language :: Python :: 3.9
License-File: LICENSE.md
Requires-Dist: adafruit-blinka-displayio
Requires-Dist: adafruit-circuitpython-display-text
Requires-Dist: adafruit-circuitpython-displayio-sh1106
